xbmc_client-0.3.0.dist-info/WHEEL
xbmc_client-0.3.0.dist-info/top_level.txt
xbmc_client-0.3.0.dist-info/METADATA
xbmc_client-0.3.0.dist-info/metadata.json
xbmc_client-0.3.0.dist-info/entry_points.txt
xbmc_client-0.3.0.dist-info/RECORD
xbmc_client-0.3.0.dist-info/DESCRIPTION.rst
xbmc_client/__init__.py
xbmc_client/xbmc_client.py
xbmc_client/config/config
