Metadata-Version: 2.0
Name: xbmc-client
Version: 0.3.0
Summary: XBMC command line client
Home-page: https://github.com/jcsaaddupuy/xbmc-client
Author: Jean-Christophe Saad-Dupuy
Author-email: saad.dupuy@gmail.com
License: WTFPL
Platform: UNKNOWN
Requires-Dist: xbmc-json (>=0.2.0)
